{"alliancePosition":"Red 1","matchNum":13,"cdropGame":1,"hpshipGame":3,"cshipSand":0,"crocketSand":0,"crossedLine":false,"isBlueAlliance":false,"cshipGame":3,"hpshipSand":1,"hpdropSand":1,"isHelp":false,"scaleLevel":3,"startHab":1,"yellow":false,"hprocketSand":2,"crocketGame":5,"techs":0,"cdropSand":0,"fouls":1,"estopped":false,"hprocketGame":4,"borked":true,"hpdropGame":1,"points":107,"matchType":"Qualifier","matchNotes":"fast, solo rocket","crRP":true,"nonFoulPoints":104,"rrocket":false,"rankingPoints":4,"lrocket":false,"habRP":true,"scoreBreakdown":{"habLineRobot1":"CrossedHabLineInSandstorm","habLineRobot2":"CrossedHabLineInSandstorm","habLineRobot3":"CrossedHabLineInSandstorm","lowRightRocketNear":"PanelAndCargo","cargoPoints":45,"topRightRocketFar":"PanelAndCargo","lowLeftRocketNear":"PanelAndCargo","midRightRocketFar":"PanelAndCargo","hatchPanelPoints":26,"lowRightRocketFar":"Panel","preMatchLevelRobot1":"HabLevel1","preMatchBay6":"Panel","preMatchLevelRobot2":"HabLevel1","habClimbPoints":21,"preMatchBay7":"Panel","preMatchLevelRobot3":"HabLevel2","preMatchBay1":"Panel","preMatchBay2":"Panel","preMatchBay3":"Panel","midLeftRocketNear":"PanelAndCargo","midRightRocketNear":"PanelAndCargo","sandStormBonusPoints":12,"topLeftRocketFar":"PanelAndCargo","midLeftRocketFar":"PanelAndCargo","foulPoints":3,"habDockingRankingPoint":true,"preMatchBay8":"Panel","teleopPoints":92,"completeRocketRankingPoint":true,"bay8":"PanelAndCargo","endgameRobot1":"HabLevel2","endgameRobot2":"HabLevel3","bay6":"Panel","endgameRobot3":"HabLevel1","lowLeftRocketFar":"None","bay7":"PanelAndCargo","topLeftRocketNear":"PanelAndCargo","bay4":"Panel","bay5":"Panel","bay2":"PanelAndCargo","bay3":"PanelAndCargo","totalPoints":107,"bay1":"PanelAndCargo","topRightRocketNear":"PanelAndCargo","rp":4},"tbaSynced":true,"teamNum":1678,"red":false}