{"alliancePosition":"Red 1","matchNum":17,"cdropGame":1,"hpshipGame":1,"cshipSand":0,"crocketSand":0,"crossedLine":false,"isBlueAlliance":false,"cshipGame":1,"hpshipSand":1,"hpdropSand":1,"isHelp":false,"scaleLevel":1,"startHab":1,"yellow":false,"hprocketSand":1,"crocketGame":4,"techs":0,"cdropSand":0,"fouls":1,"estopped":false,"hprocketGame":3,"borked":false,"hpdropGame":3,"points":85,"matchType":"Qualifier","matchNotes":"fast fluid movement","crRP":true,"nonFoulPoints":85,"rrocket":false,"rankingPoints":4,"lrocket":false,"habRP":true,"scoreBreakdown":{"habLineRobot1":"CrossedHabLineInSandstorm","habLineRobot2":"CrossedHabLineInSandstorm","habLineRobot3":"CrossedHabLineInSandstorm","lowRightRocketNear":"None","cargoPoints":36,"topRightRocketFar":"None","lowLeftRocketNear":"None","midRightRocketFar":"None","hatchPanelPoints":16,"lowRightRocketFar":"PanelAndCargo","preMatchLevelRobot1":"HabLevel1","preMatchBay6":"Panel","preMatchLevelRobot2":"HabLevel1","habClimbPoints":21,"preMatchBay7":"Panel","preMatchLevelRobot3":"HabLevel2","preMatchBay1":"Panel","preMatchBay2":"Panel","preMatchBay3":"Cargo","midLeftRocketNear":"PanelAndCargo","midRightRocketNear":"PanelAndCargo","sandStormBonusPoints":12,"topLeftRocketFar":"None","midLeftRocketFar":"None","foulPoints":0,"habDockingRankingPoint":true,"preMatchBay8":"Panel","teleopPoints":73,"completeRocketRankingPoint":true,"bay8":"Panel","endgameRobot1":"HabLevel1","endgameRobot2":"HabLevel2","bay6":"PanelAndCargo","endgameRobot3":"HabLevel3","lowLeftRocketFar":"PanelAndCargo","bay7":"PanelAndCargo","topLeftRocketNear":"PanelAndCargo","bay4":"None","bay5":"PanelAndCargo","bay2":"PanelAndCargo","bay3":"PanelAndCargo","totalPoints":85,"bay1":"PanelAndCargo","topRightRocketNear":"PanelAndCargo","rp":4},"tbaSynced":true,"teamNum":114,"red":false}