{"number":3476,"avGPSand":2.125,"isFullySync":true,"avHPDrop":1.75,"avCRocket":2.25,"avHPRocket":2.5,"avCDrop":1.25,"scaleLevels":[3,0,1],"maxScaleLevel":3.0,"avTech":0.5,"consistOffHab":true,"isRamp":false,"consistStartHab":1.0,"avFoul":0.625,"totalYellow":0.0,"sponsors":"Code Orange Robotics, Inc./Lasergraphics/Applied Medical/UST Global, Inc./Boeing/Western Digital/Exact Industries&Neighborhood Group","avHPShip":1.5,"totalRed":0.0,"startHabs":[1,1,1],"estops":0.0,"maxStartHab":1.0,"avCShip":2.125,"borks":0.0,"totalRPs":5,"totalHabRPs":1,"totalRockets":0,"totalRocketRPs":2,"groups":[],"robotNicknames":[],"scoutedName":null,"tbaName":"Code Orange","matches":[{"alliancePosition":"Blue 1","matchNum":14,"cdropGame":0,"hpshipGame":0,"cshipSand":0,"crocketSand":0,"crossedLine":false,"isBlueAlliance":true,"cshipGame":5,"hpshipSand":0,"hpdropSand":1,"isHelp":false,"scaleLevel":3,"startHab":1,"yellow":false,"hprocketSand":1,"crocketGame":4,"techs":0,"cdropSand":0,"fouls":1,"estopped":false,"hprocketGame":3,"borked":false,"hpdropGame":1,"points":78,"matchType":"Qualifier","matchNotes":"turning elevator, intake got stuck on top lvl rocket after putting cargo in  ","crRP":true,"nonFoulPoints":78,"rrocket":false,"rankingPoints":2,"lrocket":false,"habRP":true,"scoreBreakdown":{"habLineRobot1":"CrossedHabLineInSandstorm","habLineRobot2":"CrossedHabLineInSandstorm","habLineRobot3":"CrossedHabLineInSandstorm","lowRightRocketNear":"PanelAndCargo","cargoPoints":33,"topRightRocketFar":"PanelAndCargo","lowLeftRocketNear":"PanelAndCargo","midRightRocketFar":"PanelAndCargo","hatchPanelPoints":18,"lowRightRocketFar":"None","preMatchLevelRobot1":"HabLevel1","preMatchBay6":"Panel","preMatchLevelRobot2":"HabLevel1","habClimbPoints":18,"preMatchBay7":"Panel","preMatchLevelRobot3":"HabLevel1","preMatchBay1":"Panel","preMatchBay2":"Panel","preMatchBay3":"Panel","midLeftRocketNear":"None","midRightRocketNear":"None","sandStormBonusPoints":9,"topLeftRocketFar":"PanelAndCargo","midLeftRocketFar":"PanelAndCargo","foulPoints":0,"habDockingRankingPoint":true,"preMatchBay8":"Panel","teleopPoints":69,"completeRocketRankingPoint":true,"bay8":"Panel","endgameRobot1":"HabLevel3","endgameRobot2":"HabLevel2","bay6":"Panel","endgameRobot3":"None","lowLeftRocketFar":"None","bay7":"Panel","topLeftRocketNear":"PanelAndCargo","bay4":"None","bay5":"PanelAndCargo","bay2":"PanelAndCargo","bay3":"PanelAndCargo","totalPoints":78,"bay1":"Panel","topRightRocketNear":"PanelAndCargo","rp":2},"tbaSynced":true,"teamNum":3476,"red":false},{"alliancePosition":"Red 2","matchNum":29,"cdropGame":2,"hpshipGame":1,"cshipSand":0,"crocketSand":0,"crossedLine":false,"isBlueAlliance":false,"cshipGame":4,"hpshipSand":1,"hpdropSand":1,"isHelp":false,"scaleLevel":0,"startHab":1,"yellow":false,"hprocketSand":1,"crocketGame":1,"techs":0,"cdropSand":1,"fouls":0,"estopped":false,"hprocketGame":1,"borked":false,"hpdropGame":1,"points":77,"matchType":"Qualifier","matchNotes":"went on defence (not super effective against citrus), stopped moving, but started moving again at the last part to go back to hab. not sure what happened there","crRP":false,"nonFoulPoints":77,"rrocket":false,"rankingPoints":2,"lrocket":false,"habRP":false,"scoreBreakdown":{"habLineRobot1":"CrossedHabLineInSandstorm","habLineRobot2":"CrossedHabLineInSandstorm","habLineRobot3":"CrossedHabLineInSandstorm","lowRightRocketNear":"None","cargoPoints":27,"topRightRocketFar":"None","lowLeftRocketNear":"None","midRightRocketFar":"PanelAndCargo","hatchPanelPoints":20,"lowRightRocketFar":"PanelAndCargo","preMatchLevelRobot1":"HabLevel2","preMatchBay6":"Panel","preMatchLevelRobot2":"HabLevel1","habClimbPoints":15,"preMatchBay7":"Panel","preMatchLevelRobot3":"HabLevel2","preMatchBay1":"Panel","preMatchBay2":"Panel","preMatchBay3":"Panel","midLeftRocketNear":"Panel","midRightRocketNear":"Panel","sandStormBonusPoints":15,"topLeftRocketFar":"None","midLeftRocketFar":"PanelAndCargo","foulPoints":0,"habDockingRankingPoint":false,"preMatchBay8":"Panel","teleopPoints":62,"completeRocketRankingPoint":false,"bay8":"PanelAndCargo","endgameRobot1":"None","endgameRobot2":"HabLevel1","bay6":"PanelAndCargo","endgameRobot3":"HabLevel3","lowLeftRocketFar":"PanelAndCargo","bay7":"PanelAndCargo","topLeftRocketNear":"Panel","bay4":"PanelAndCargo","bay5":"Panel","bay2":"PanelAndCargo","bay3":"Panel","totalPoints":77,"bay1":"Panel","topRightRocketNear":"Panel","rp":2},"tbaSynced":true,"teamNum":3476,"red":false},{"alliancePosition":"Red 3","matchNum":40,"cdropGame":1,"hpshipGame":1,"cshipSand":0,"crocketSand":1,"crossedLine":false,"isBlueAlliance":false,"cshipGame":1,"hpshipSand":1,"hpdropSand":1,"isHelp":false,"scaleLevel":1,"startHab":1,"yellow":false,"hprocketSand":1,"crocketGame":2,"techs":1,"cdropSand":0,"fouls":1,"estopped":false,"hprocketGame":2,"borked":false,"hpdropGame":1,"points":77,"matchType":"Qualifier","matchNotes":"fast smooth movement,climbed with z arm","crRP":true,"nonFoulPoints":77,"rrocket":false,"rankingPoints":1,"lrocket":false,"habRP":false,"scoreBreakdown":{"habLineRobot1":"CrossedHabLineInSandstorm","habLineRobot2":"CrossedHabLineInSandstorm","habLineRobot3":"CrossedHabLineInSandstorm","lowRightRocketNear":"PanelAndCargo","cargoPoints":36,"topRightRocketFar":"None","lowLeftRocketNear":"PanelAndCargo","midRightRocketFar":"PanelAndCargo","hatchPanelPoints":20,"lowRightRocketFar":"Panel","preMatchLevelRobot1":"HabLevel1","preMatchBay6":"Panel","preMatchLevelRobot2":"HabLevel2","habClimbPoints":9,"preMatchBay7":"Panel","preMatchLevelRobot3":"HabLevel1","preMatchBay1":"Cargo","preMatchBay2":"Cargo","preMatchBay3":"Panel","midLeftRocketNear":"None","midRightRocketNear":"None","sandStormBonusPoints":12,"topLeftRocketFar":"None","midLeftRocketFar":"PanelAndCargo","foulPoints":0,"habDockingRankingPoint":false,"preMatchBay8":"Panel","teleopPoints":65,"completeRocketRankingPoint":true,"bay8":"Panel","endgameRobot1":"HabLevel1","endgameRobot2":"HabLevel1","bay6":"PanelAndCargo","endgameRobot3":"HabLevel1","lowLeftRocketFar":"None","bay7":"PanelAndCargo","topLeftRocketNear":"PanelAndCargo","bay4":"PanelAndCargo","bay5":"None","bay2":"PanelAndCargo","bay3":"PanelAndCargo","totalPoints":77,"bay1":"PanelAndCargo","topRightRocketNear":"PanelAndCargo","rp":1},"tbaSynced":true,"teamNum":3476,"red":false}],"matchNotes":{"40":"fast smooth movement,climbed with z arm","29":"went on defence (not super effective against citrus), stopped moving, but started moving again at the last part to go back to hab. not sure what happened there","14":"turning elevator, intake got stuck on top lvl rocket after putting cargo in  "},"consistScaleLevel":3.0}