{"number":5818,"avGPSand":2.5,"isFullySync":true,"avHPDrop":1.375,"avCRocket":1.75,"avHPRocket":2.625,"avCDrop":0.875,"scaleLevels":[3,3,3],"maxScaleLevel":3.0,"avTech":0.5,"consistOffHab":true,"isRamp":false,"consistStartHab":2.0,"avFoul":0.75,"totalYellow":0.0,"sponsors":"Bosch/Virgil Elings/Architectural Millwork/FLIR/Rincon Engineering/Check Yourself Inc./Lockheed Martin/Neal Feay Company/Subsea Circuits/Gracewood/L3/Arthrex/ARMABOT&Riviera Robotics","avHPShip":2.25,"totalRed":0.0,"startHabs":[2,2,2],"estops":0.0,"maxStartHab":2.0,"avCShip":1.875,"borks":0.0,"totalRPs":4,"totalHabRPs":2,"totalRockets":0,"totalRocketRPs":0,"groups":[],"robotNicknames":[],"scoutedName":null,"tbaName":"Riviera Robotics","matches":[{"alliancePosition":"Blue 3","matchNum":16,"cdropGame":1,"hpshipGame":2,"cshipSand":0,"crocketSand":0,"crossedLine":false,"isBlueAlliance":true,"cshipGame":1,"hpshipSand":2,"hpdropSand":0,"isHelp":false,"scaleLevel":3,"startHab":2,"yellow":false,"hprocketSand":0,"crocketGame":2,"techs":0,"cdropSand":0,"fouls":0,"estopped":false,"hprocketGame":3,"borked":false,"hpdropGame":1,"points":71,"matchType":"Qualifier","matchNotes":"interesting. better at hatches than cargo. fast. 10/10 driving would pick","crRP":false,"nonFoulPoints":71,"rrocket":false,"rankingPoints":2,"lrocket":false,"habRP":false,"scoreBreakdown":{"habLineRobot1":"CrossedHabLineInSandstorm","habLineRobot2":"CrossedHabLineInSandstorm","habLineRobot3":"CrossedHabLineInSandstorm","lowRightRocketNear":"PanelAndCargo","cargoPoints":24,"topRightRocketFar":"PanelAndCargo","lowLeftRocketNear":"PanelAndCargo","midRightRocketFar":"None","hatchPanelPoints":20,"lowRightRocketFar":"None","preMatchLevelRobot1":"HabLevel2","preMatchBay6":"Panel","preMatchLevelRobot2":"HabLevel1","habClimbPoints":12,"preMatchBay7":"Panel","preMatchLevelRobot3":"HabLevel2","preMatchBay1":"Cargo","preMatchBay2":"Cargo","preMatchBay3":"Cargo","midLeftRocketNear":"None","midRightRocketNear":"None","sandStormBonusPoints":15,"topLeftRocketFar":"PanelAndCargo","midLeftRocketFar":"Panel","foulPoints":0,"habDockingRankingPoint":false,"preMatchBay8":"Panel","teleopPoints":56,"completeRocketRankingPoint":false,"bay8":"Panel","endgameRobot1":"None","endgameRobot2":"None","bay6":"PanelAndCargo","endgameRobot3":"HabLevel3","lowLeftRocketFar":"Panel","bay7":"Panel","topLeftRocketNear":"None","bay4":"PanelAndCargo","bay5":"None","bay2":"PanelAndCargo","bay3":"PanelAndCargo","totalPoints":71,"bay1":"Panel","topRightRocketNear":"None","rp":2},"tbaSynced":true,"teamNum":5818,"red":false},{"alliancePosition":"Red 1","matchNum":25,"cdropGame":1,"hpshipGame":1,"cshipSand":0,"crocketSand":0,"crossedLine":false,"isBlueAlliance":false,"cshipGame":1,"hpshipSand":2,"hpdropSand":1,"isHelp":false,"scaleLevel":3,"startHab":2,"yellow":false,"hprocketSand":1,"crocketGame":2,"techs":0,"cdropSand":0,"fouls":1,"estopped":false,"hprocketGame":2,"borked":false,"hpdropGame":0,"points":67,"matchType":"Qualifier","matchNotes":"struggled a little when defended","crRP":false,"nonFoulPoints":67,"rrocket":false,"rankingPoints":1,"lrocket":false,"habRP":true,"scoreBreakdown":{"habLineRobot1":"CrossedHabLineInSandstorm","habLineRobot2":"CrossedHabLineInSandstorm","habLineRobot3":"CrossedHabLineInSandstorm","lowRightRocketNear":"PanelAndCargo","cargoPoints":18,"topRightRocketFar":"Panel","lowLeftRocketNear":"PanelAndCargo","midRightRocketFar":"None","hatchPanelPoints":16,"lowRightRocketFar":"Panel","preMatchLevelRobot1":"HabLevel2","preMatchBay6":"Panel","preMatchLevelRobot2":"HabLevel1","habClimbPoints":21,"preMatchBay7":"Panel","preMatchLevelRobot3":"HabLevel1","preMatchBay1":"Cargo","preMatchBay2":"Cargo","preMatchBay3":"Cargo","midLeftRocketNear":"None","midRightRocketNear":"None","sandStormBonusPoints":12,"topLeftRocketFar":"PanelAndCargo","midLeftRocketFar":"None","foulPoints":0,"habDockingRankingPoint":true,"preMatchBay8":"Panel","teleopPoints":55,"completeRocketRankingPoint":false,"bay8":"Panel","endgameRobot1":"HabLevel3","endgameRobot2":"HabLevel1","bay6":"Panel","endgameRobot3":"HabLevel2","lowLeftRocketFar":"None","bay7":"Panel","topLeftRocketNear":"None","bay4":"PanelAndCargo","bay5":"None","bay2":"PanelAndCargo","bay3":"PanelAndCargo","totalPoints":67,"bay1":"None","topRightRocketNear":"None","rp":1},"tbaSynced":true,"teamNum":5818,"red":false},{"alliancePosition":"Red 3","matchNum":51,"cdropGame":1,"hpshipGame":1,"cshipSand":0,"crocketSand":1,"crossedLine":false,"isBlueAlliance":false,"cshipGame":3,"hpshipSand":1,"hpdropSand":1,"isHelp":false,"scaleLevel":3,"startHab":2,"yellow":false,"hprocketSand":1,"crocketGame":1,"techs":1,"cdropSand":0,"fouls":1,"estopped":false,"hprocketGame":2,"borked":false,"hpdropGame":1,"points":70,"matchType":"Qualifier","matchNotes":"DONT PICK THEY ARE MEAN THEY BROKE OUR ENCODERS","crRP":false,"nonFoulPoints":70,"rrocket":false,"rankingPoints":1,"lrocket":false,"habRP":true,"scoreBreakdown":{"habLineRobot1":"CrossedHabLineInSandstorm","habLineRobot2":"CrossedHabLineInSandstorm","habLineRobot3":"CrossedHabLineInSandstorm","lowRightRocketNear":"None","cargoPoints":24,"topRightRocketFar":"None","lowLeftRocketNear":"None","midRightRocketFar":"None","hatchPanelPoints":16,"lowRightRocketFar":"PanelAndCargo","preMatchLevelRobot1":"HabLevel1","preMatchBay6":"Cargo","preMatchLevelRobot2":"HabLevel1","habClimbPoints":18,"preMatchBay7":"Cargo","preMatchLevelRobot3":"HabLevel2","preMatchBay1":"Panel","preMatchBay2":"Panel","preMatchBay3":"Panel","midLeftRocketNear":"Panel","midRightRocketNear":"None","sandStormBonusPoints":12,"topLeftRocketFar":"None","midLeftRocketFar":"None","foulPoints":0,"habDockingRankingPoint":true,"preMatchBay8":"Cargo","teleopPoints":58,"completeRocketRankingPoint":false,"bay8":"None","endgameRobot1":"HabLevel1","endgameRobot2":"HabLevel1","bay6":"PanelAndCargo","endgameRobot3":"HabLevel3","lowLeftRocketFar":"PanelAndCargo","bay7":"Panel","topLeftRocketNear":"Panel","bay4":"PanelAndCargo","bay5":"PanelAndCargo","bay2":"PanelAndCargo","bay3":"PanelAndCargo","totalPoints":70,"bay1":"PanelAndCargo","topRightRocketNear":"None","rp":1},"tbaSynced":true,"teamNum":5818,"red":false}],"matchNotes":{"16":"interesting. better at hatches than cargo. fast. 10/10 driving would pick","51":"DONT PICK THEY ARE MEAN THEY BROKE OUR ENCODERS","25":"struggled a little when defended"},"consistScaleLevel":3.0}