{"red":false,"teamNum":4698,"startHab":2,"estopped":false,"scaleLevel":2,"borked":true,"matchNum":38,"matchNotes":"had trouble putting hp on.  difficulties driving around other robots.  ran into teammate and dropped their hatch ","driverRank":0,"alliancePosition":null,"matchType":null,"hpshipGame":0,"isBlueAlliance":false,"techs":null,"rankingPoints":0,"lrocket":false,"cshipSand":0,"hprocketSand":0,"habRP":false,"hpdropSand":0,"cdropGame":0,"nonFoulPoints":0,"crRP":false,"cshipGame":0,"hpshipSand":0,"scoreBreakdown":null,"hpdropGame":0,"tbaSynced":false,"crocketSand":0,"yellow":false,"crocketGame":0,"fouls":null,"hprocketGame":0,"crossedLine":false,"points":0,"rrocket":false,"cdropSand":0,"isHelp":false}