{"matchNum":64,"alliancePosition":null,"red":false,"matchType":"Qualifier","teamNum":2473,"isBlueAlliance":false,"hprocketSand":0,"crocketSand":0,"estopped":false,"rrocket":false,"crRP":false,"tbaSynced":true,"cdropGame":1,"matchNotes":"intake didn't work... yeah pretty bad tbh ","hpshipGame":0,"cshipGame":1,"hprocketGame":1,"crossedLine":false,"cdropSand":0,"fouls":0,"hpshipSand":0,"crocketGame":3,"isHelp":false,"scaleLevel":0,"hpdropSand":1,"nonFoulPoints":29,"lrocket":false,"cshipSand":0,"habRP":false,"techs":0,"rankingPoints":0,"borked":false,"startHab":1,"scoreBreakdown":{"foulCount":0,"topRightRocketFar":"None","midRightRocketFar":"None","hatchPanelPoints":2,"lowRightRocketFar":"Panel","preMatchLevelRobot1":"HabLevel1","preMatchLevelRobot2":"HabLevel2","preMatchLevelRobot3":"HabLevel1","midRightRocketNear":"None","topLeftRocketFar":"None","techFoulCount":0,"teleopPoints":20,"topLeftRocketNear":"None","autoPoints":9,"rp":0,"habLineRobot1":"CrossedHabLineInSandstorm","habLineRobot2":"CrossedHabLineInSandstorm","habLineRobot3":"CrossedHabLineInTeleop","lowRightRocketNear":"None","cargoPoints":18,"lowLeftRocketNear":"None","completedRocketNear":false,"completedRocketFar":false,"preMatchBay6":"Panel","habClimbPoints":0,"preMatchBay7":"Panel","preMatchBay1":"Panel","preMatchBay2":"Panel","preMatchBay3":"Panel","midLeftRocketNear":"None","sandStormBonusPoints":9,"midLeftRocketFar":"None","foulPoints":3,"habDockingRankingPoint":false,"preMatchBay8":"Panel","completeRocketRankingPoint":false,"bay8":"PanelAndCargo","endgameRobot1":"None","endgameRobot2":"None","adjustPoints":0,"bay6":"PanelAndCargo","endgameRobot3":"None","lowLeftRocketFar":"None","bay7":"PanelAndCargo","bay4":"None","bay5":"None","bay2":"PanelAndCargo","bay3":"PanelAndCargo","totalPoints":32,"bay1":"PanelAndCargo","topRightRocketNear":"None"},"hpdropGame":2,"yellow":false,"points":32}